Adafruit_MAX9744-1.0.2.dist-info/metadata.json
Adafruit_MAX9744-1.0.2.dist-info/METADATA
Adafruit_MAX9744-1.0.2.dist-info/RECORD
Adafruit_MAX9744-1.0.2.dist-info/WHEEL
Adafruit_MAX9744-1.0.2.dist-info/DESCRIPTION.rst
Adafruit_MAX9744-1.0.2.dist-info/dependency_links.txt
Adafruit_MAX9744-1.0.2.dist-info/top_level.txt
Adafruit_MAX9744/MAX9744.py
Adafruit_MAX9744/__init__.py
