Metadata-Version: 2.0
Name: Adafruit-MAX9744
Version: 1.0.2
Summary: Library for controlling the MAX9744 class D amplifier with I2C volume control on a Raspberry Pi or Beaglebone Black.
Home-page: https://github.com/adafruit/Adafruit_Python_MAX9744/
Author: Tony DiCola
Author-email: tdicola@adafruit.com
License: MIT
Platform: UNKNOWN
Requires-Dist: Adafruit-GPIO (>=0.9.0)
